napari_tracks/__init__.py
napari_tracks/tracks.py
napari_tracks/_tests/__init__.py
napari_tracks/_tests/test_tracks.py
napari_tracks-0.0.2.dist-info/LICENSE
napari_tracks-0.0.2.dist-info/METADATA
napari_tracks-0.0.2.dist-info/WHEEL
napari_tracks-0.0.2.dist-info/entry_points.txt
napari_tracks-0.0.2.dist-info/top_level.txt
napari_tracks-0.0.2.dist-info/RECORD
